<?xml version="1.0" encoding="UTF-8"?>
<CONFIG>
  <ActionsContent>
    <Group Category="SL">
      <ZAction Name="ACN_slagcabCom" Command="slagcab" Img="#D()" Caption="Start command panels for autocabeling SL"/>
      <ZAction Name="ACN_vBuildSSSchema" Command="vBuildSSSchema" Img="#vSS" Caption="Start building vSS Schema"/>
      <ZAction Name="ACN_vBuildELSchema" Command="vBuildELSchema" Img="#vEL" Caption="Start building vEL Schema"/>
      <ZAction Name="ACN_agslr" Command="AGSLROOM" Img="#ASL" Caption="Start command ASL"/>
      <ZAction Name="ACN_SupeLine" Command="DrawSuperLine" Img="superline.bmp" Caption="SuperLine" ShortCut="CTRL+ALT+S" SecondaryShortCuts="S"/>
      <ZAction Name="ACN_SupeLineHT1" Command="DrawSuperLine(1)" Img="#1" Caption="SuperLine" SecondaryShortCuts="1"/>
      <ZAction Name="ACN_SupeLineHT2" Command="DrawSuperLine(2)" Img="#2" Caption="SuperLine" SecondaryShortCuts="2"/>
      <ZAction Name="ACN_SupeLineHT3" Command="DrawSuperLine(3)" Img="#3" Caption="SuperLine" SecondaryShortCuts="3"/>
      <ZAction Name="ACN_uzvaddconnection" Command="uzvaddconnection" Img="#C+" Caption="Add connection"/>
      <ZAction Name="ACN_uzvremoveconnection" Command="uzvremoveconnection" Img="#ะก-" Caption="Remove connection"/>
      <ZAction Name="ACN_managerEM" Command="manem" Img="#MEM" Caption="Manager electrical model"/>
    </Group>
  </ActionsContent>
</CONFIG>