<?xml version="1.0"?>
<CONFIG>
  <MainConfig>
    <Nodes ChildCount="1">
      <Item1 Name="MainForm" Type="CustomSite" ChildCount="1">
        <Bounds Width="797" Height="293"/>
        <Item1 Name="AnchorDockSite3" Type="Layout" ChildCount="9">
          <Bounds Top="31" Width="797" Height="240" SplitterPos="26"/>
          <Anchors Align="Bottom"/>
          <Item1 Name="PageControl" Type="Control">
            <Bounds Left="146" Width="619" Height="157"/>
            <Anchors Left="AnchorDockSplitter4" Right="AnchorDockSplitter2" Bottom="AnchorDockSplitter5"/>
          </Item1>
          <Item2 Name="AnchorDockSplitter2" Type="SplitterVertical">
            <Bounds Left="765" Width="4" Height="240"/>
          </Item2>
          <Item3 Name="ToolBarR" Type="Control">
            <Bounds Left="769" Width="28" Height="240"/>
            <Anchors Left="AnchorDockSplitter2"/>
          </Item3>
          <Item4 Name="AnchorDockSplitter3" Type="SplitterHorizontal">
            <Bounds Top="228" Width="765" Height="4"/>
            <Anchors Right="AnchorDockSplitter2"/>
          </Item4>
          <Item5 Name="ToolBarD" Type="Control">
            <Bounds Top="232" Width="765" Height="8"/>
            <Anchors Top="AnchorDockSplitter3" Right="AnchorDockSplitter2"/>
          </Item5>
          <Item6 Name="AnchorDockSplitter4" Type="SplitterVertical">
            <Bounds Left="142" Width="4" Height="228"/>
            <Anchors Bottom="AnchorDockSplitter3"/>
          </Item6>
          <Item7 Name="ObjectInspector" Type="Control">
            <Bounds Width="142" Height="228"/>
            <Anchors Right="AnchorDockSplitter4" Bottom="AnchorDockSplitter3"/>
          </Item7>
          <Item8 Name="AnchorDockSplitter5" Type="SplitterHorizontal">
            <Bounds Top="157" Left="146" Width="619" Height="4"/>
            <Anchors Left="AnchorDockSplitter4" Right="AnchorDockSplitter2"/>
          </Item8>
          <Item9 Name="CommandLine" Type="Control">
            <Bounds Top="161" Left="146" Width="619" Height="67"/>
            <Anchors Top="AnchorDockSplitter5" Left="AnchorDockSplitter4" Right="AnchorDockSplitter2" Bottom="AnchorDockSplitter3"/>
          </Item9>
        </Item1>
      </Item1>
    </Nodes>
  </MainConfig>
</CONFIG>
